CHANGELOG.txt
LICENCE.txt
MANIFEST.in
README.md
setup.py
RPScissors/__init__.py
rpscissors.egg-info/PKG-INFO
rpscissors.egg-info/SOURCES.txt
rpscissors.egg-info/dependency_links.txt
rpscissors.egg-info/top_level.txt