Metadata-Version: 2.4
Name: rpscissors
Version: 0.0.3
Summary: A Rock Paper Scissors game
Author: Iven Boxem
Author-email: boxemivenruben@gmail.com
License: MIT
Keywords: rock paper scissors game
Classifier: Development Status :: 5 - Production/Stable
Classifier: Intended Audience :: Education
Classifier: License :: OSI Approved :: MIT License
Classifier: Programming Language :: Python :: 3
Classifier: Operating System :: OS Independent
Requires-Python: >=3.8
License-File: LICENCE.txt
Dynamic: author
Dynamic: author-email
Dynamic: classifier
Dynamic: description
Dynamic: description-content-type
Dynamic: keywords
Dynamic: license
Dynamic: license-file
Dynamic: requires-python
Dynamic: summary
